setup.cfg
setup.py
assurest/__init__.py
assurest.egg-info/PKG-INFO
assurest.egg-info/SOURCES.txt
assurest.egg-info/dependency_links.txt
assurest.egg-info/requires.txt
assurest.egg-info/top_level.txt