Metadata-Version: 1.1
Name: assurest
Version: 0.2
Summary: Nice looking tests for REST servers
Home-page: https://github.com/staudt/assurest
Author: Ricardo Staudt
Author-email: ricardost@gmail.com
License: MIT
Keywords: test setuptools development
Platform: UNKNOWN
Classifier: Development Status :: 3 - Alpha
Classifier: Intended Audience :: Developers
Classifier: Topic :: Software Development :: Build Tools
Classifier: License :: OSI Approved :: MIT License
Classifier: Programming Language :: Python :: 2
Classifier: Programming Language :: Python :: 2.7
Classifier: Programming Language :: Python :: 3
Classifier: Programming Language :: Python :: 3.4
Classifier: Programming Language :: Python :: 3.5
Classifier: Programming Language :: Python :: 3.6
